.gitignore
.travis.yml
CITATION.cff
LICENSE
README.rst
pyproject.toml
requirements.txt
setup.cfg
setup.py
.github/workflows/publish-to-pypi.yml
.github/workflows/python-package.yml
docs/_static/golfir_logo.png
golfir/__init__.py
golfir/catalog.py
golfir/irac.py
golfir/model.py
golfir/pipeline.py
golfir/utils.py
golfir/version.py
golfir.egg-info/PKG-INFO
golfir.egg-info/SOURCES.txt
golfir.egg-info/dependency_links.txt
golfir.egg-info/requires.txt
golfir.egg-info/top_level.txt
golfir/data/bcd_ch1.header
golfir/data/bcd_ch2.header
golfir/data/bcd_ch3.header
golfir/data/bcd_ch4.header
golfir/data/libralato_hawki_chip1.crpix.header
golfir/data/libralato_hawki_chip2.crpix.header
golfir/data/libralato_hawki_chip3.crpix.header
golfir/data/libralato_hawki_chip4.crpix.header
golfir/data/make_headers.py
golfir/data/spitzer_ch1_zodi_healpy_16.fits
golfir/data/psf/README.md
golfir/data/psf/irac_ch1_cold_0_psf.fits
golfir/data/psf/irac_ch1_cold_1_psf.fits
golfir/data/psf/irac_ch1_cold_psf.fits
golfir/data/psf/irac_ch1_warm_0_psf.fits
golfir/data/psf/irac_ch1_warm_1_psf.fits
golfir/data/psf/irac_ch1_warm_2_psf.fits
golfir/data/psf/irac_ch1_warm_3_psf.fits
golfir/data/psf/irac_ch1_warm_4_psf.fits
golfir/data/psf/irac_ch1_warm_5_psf.fits
golfir/data/psf/irac_ch1_warm_6_psf.fits
golfir/data/psf/irac_ch1_warm_7_psf.fits
golfir/data/psf/irac_ch1_warm_8_psf.fits
golfir/data/psf/irac_ch1_warm_psf.fits
golfir/data/psf/irac_ch2_cold_0_psf.fits
golfir/data/psf/irac_ch2_cold_1_psf.fits
golfir/data/psf/irac_ch2_cold_psf.fits
golfir/data/psf/irac_ch2_warm_0_psf.fits
golfir/data/psf/irac_ch2_warm_1_psf.fits
golfir/data/psf/irac_ch2_warm_2_psf.fits
golfir/data/psf/irac_ch2_warm_3_psf.fits
golfir/data/psf/irac_ch2_warm_4_psf.fits
golfir/data/psf/irac_ch2_warm_5_psf.fits
golfir/data/psf/irac_ch2_warm_6_psf.fits
golfir/data/psf/irac_ch2_warm_7_psf.fits
golfir/data/psf/irac_ch2_warm_8_psf.fits
golfir/data/psf/irac_ch2_warm_psf.fits
golfir/data/psf/irac_ch3_cold_0_psf.fits
golfir/data/psf/irac_ch3_cold_1_psf.fits
golfir/data/psf/irac_ch3_cold_psf.fits
golfir/data/psf/irac_ch4_cold_0_psf.fits
golfir/data/psf/irac_ch4_cold_1_psf.fits
