Metadata-Version: 2.1
Name: golfir
Version: 1.0.3
Summary: Great Observatories Legacy Fields: IR tools
Home-page: https://github.com/gbrammer/golfir
Author: G. Brammer
Author-email: gbrammer@gmail.com
License: MIT
Project-URL: Documentation, https://golfir.readthedocs.io/
Project-URL: Source, https://github.com/gbrammer/golfir
Project-URL: Tracker, https://github.com/gbrammer/golfir/issues
Classifier: Development Status :: 3 - Alpha
Classifier: Intended Audience :: Science/Research
Classifier: Topic :: Scientific/Engineering :: Astronomy
Requires-Python: >=3.7
Provides-Extra: test
Provides-Extra: docs
License-File: LICENSE
